humiolib/HumioClient.py
humiolib/HumioExceptions.py
humiolib/QueryJob.py
humiolib/WebCaller.py
humiolib/__init__.py
humiolib/__main__.py
humiolib/cli.py
humiolib-0.2.6.dist-info/AUTHORS.rst
humiolib-0.2.6.dist-info/LICENSE
humiolib-0.2.6.dist-info/METADATA
humiolib-0.2.6.dist-info/WHEEL
humiolib-0.2.6.dist-info/entry_points.txt
humiolib-0.2.6.dist-info/top_level.txt
humiolib-0.2.6.dist-info/RECORD
