Metadata-Version: 2.1
Name: humiolib
Version: 0.2.6
Summary: Python SDK for connecting to Humio
Home-page: https://github.com/humio/python-humio
Author: Humio ApS
Author-email: integrations@humio.com
License: Apache-2.0
Project-URL: Documentation, https://python-humio.readthedocs.io/
Project-URL: Changelog, https://python-humio.readthedocs.io/en/latest/changelog.html
Project-URL: Issue Tracker, https://github.com/humio/python-humio/issues
Keywords: humio,log management
Classifier: Development Status :: 5 - Production/Stable
Classifier: Intended Audience :: Developers
Classifier: License :: OSI Approved :: Apache Software License
Classifier: Operating System :: Unix
Classifier: Operating System :: POSIX
Classifier: Operating System :: Microsoft :: Windows
Classifier: Programming Language :: Python
Classifier: Programming Language :: Python :: 3
Classifier: Programming Language :: Python :: 3.5
Classifier: Programming Language :: Python :: 3.6
Classifier: Programming Language :: Python :: 3.7
Classifier: Programming Language :: Python :: 3.8
Classifier: Programming Language :: Python :: Implementation :: CPython
Classifier: Programming Language :: Python :: Implementation :: PyPy
Classifier: Topic :: System :: Logging
Classifier: Topic :: System :: Monitoring
Requires-Python: >=3.5
License-File: LICENSE
License-File: AUTHORS.rst
Requires-Dist: requests
Requires-Dist: pytest
Requires-Dist: vcrpy
